cffsubr/__init__.py
cffsubr/__main__.py
cffsubr/_version.py
cffsubr/tx.exe
cffsubr-0.4.0.dist-info/licenses/LICENSE
cffsubr-0.4.0.dist-info/licenses/NOTICE
cffsubr-0.4.0.dist-info/METADATA
cffsubr-0.4.0.dist-info/WHEEL
cffsubr-0.4.0.dist-info/entry_points.txt
cffsubr-0.4.0.dist-info/top_level.txt
cffsubr-0.4.0.dist-info/RECORD
